<?xml version="1.0" encoding="UTF-8"?>
<oslc4j_tc:Toolchain xmi:version="2.0" xmlns:xmi="http://www.omg.org/XMI" xmlns:xsi="http://www.w3.org/2001/XMLSchema-instance" xmlns:oslc4j_ai="http://org.eclipse.lyo/oslc4j/adaptorInterface" xmlns:oslc4j_tc="http://org.eclipse.lyo/oslc4j/toolChain" name="SCOTT Sandbox">
  <adaptorInterfaces name="Warehouse Controller" javaClassBaseNamespace="se.ericsson.cf.scott.sandbox.whc" javaFilesBasePath="../webapp-whc/src/main/java/" jspFilesBasePath="../webapp-whc/src/main/webapp/" javascriptFilesBasePath="../webapp-whc/src/main/webapp/">
    <serviceProviderCatalog title="Service Provider Catalog" description="Service Provider Catalog">
      <serviceProviders title="Twin SP" description="Service Provider">
        <services>
          <domainSpecification href="../model-domain-pddl/spec.xmi#//@domainSpecifications[name='SCOTT%20PDDL%202.1%20subset%20spec']"/>
          <basicCapabilities>
            <resourceTypes href="../model-domain-pddl/spec.xmi#//@domainSpecifications[name='SCOTT%20PDDL%202.1%20subset%20spec']/@resources[name='Plan']"/>
          </basicCapabilities>
        </services>
        <services domainSpecification="//@specification/@domainSpecifications[name='MissionOntology']" serviceNamespace="independantOfServiceProvider">
          <creationFactories title="RegistrationCF" label="Registration Creation Factory" creationURI="register">
            <resourceTypes href="../model-domain-pddl/spec.xmi#//@domainSpecifications[name='Twins%20Domain']/@resources[name='RegistrationMessage']"/>
          </creationFactories>
        </services>
      </serviceProviders>
    </serviceProviderCatalog>
    <specification/>
    <requiredAdaptors xsi:type="oslc4j_ai:GenericRequiredAdaptor" serviceProviderCatalogURI="http://your.host.com/adaptor/services/catalog/singleton" name="GenericRequiredAdaptor"/>
  </adaptorInterfaces>
  <adaptorInterfaces name="PlannerReasoner placeholder" javaClassBaseNamespace="se.ericsson.cf.scott.sandbox.planner" javaFilesBasePath="../webapp-planner-placeholder/src/main/java/" jspFilesBasePath="../webapp-planner-placeholder/src/main/webapp/" javascriptFilesBasePath="../webapp-planner-placeholder/src/main/webapp/">
    <serviceProviderCatalog title="Planner Reasoner catalog">
      <serviceProviders title="robot" description="Robot planner provider">
        <services>
          <domainSpecification href="../model-domain-pddl/spec.xmi#//@domainSpecifications[name='SCOTT%20PDDL%202.1%20subset%20spec']"/>
          <basicCapabilities/>
        </services>
      </serviceProviders>
    </serviceProviderCatalog>
    <specification/>
    <requiredAdaptors xsi:type="oslc4j_ai:GenericRequiredAdaptor" serviceProviderCatalogURI="http://your.host.com/adaptor/services/catalog/singleton" name="GenericRequiredAdaptor"/>
  </adaptorInterfaces>
  <adaptorInterfaces name="Twin" javaClassBaseNamespace="se.ericsson.cf.scott.sandbox.twin" javaFilesBasePath="../webapp-twin-robot/src/main/java/" jspFilesBasePath="../webapp-twin-robot/src/main/webapp/" javascriptFilesBasePath="../webapp-twin-robot/src/main/webapp/">
    <serviceProviderCatalog title="Service Provider Catalog" description="Service Provider Catalog">
      <serviceProviders title="Twin SP" description="A Service Provider for Twins" serviceNamespace="twins" instanceID="{twinKind}/{twinId}">
        <services>
          <domainSpecification href="../model-domain-pddl/spec.xmi#//@domainSpecifications[name='Twins%20Domain']"/>
          <creationFactories title="PlanFactory" label="CF to schedule new plans for execution" creationURI="create">
            <resourceTypes href="../model-domain-pddl/spec.xmi#//@domainSpecifications[name='Twins%20Domain']/@resources[name='PlanExecutionRequest']"/>
          </creationFactories>
          <usages>planExecution</usages>
        </services>
        <services>
          <domainSpecification href="../model-domain-pddl/spec.xmi#//@domainSpecifications[name='SCOTT%20Warehouse']"/>
          <basicCapabilities instanceID="">
            <resourceTypes href="../model-domain-pddl/spec.xmi#//@domainSpecifications[name='SCOTT%20Warehouse']/@resources[name='ActionExecutionReport']"/>
          </basicCapabilities>
          <usages>executionReports</usages>
        </services>
      </serviceProviders>
      <serviceProviders title="Independent" description="Generic SP for SP-independent services" serviceNamespace="independent">
        <services domainSpecification="//@specification/@domainSpecifications[name='MissionOntology']" serviceNamespace="independantOfServiceProvider">
          <creationFactories title="Registration CF" label="Twin Registration factory" creationURI="register">
            <resourceTypes href="../model-domain-pddl/spec.xmi#//@domainSpecifications[name='Twins%20Domain']/@resources[name='DeviceRegistrationMessage']"/>
          </creationFactories>
        </services>
      </serviceProviders>
    </serviceProviderCatalog>
    <specification/>
  </adaptorInterfaces>
  <adaptorInterfaces name="PlanExecutor" javaClassBaseNamespace="se.ericsson.cf.scott.sandbox.executor" javaFilesBasePath="../webapp-executor/src/main/java/" jspFilesBasePath="../webapp-executor/src/main/webapp/" javascriptFilesBasePath="../webapp-executor/src/main/webapp/">
    <serviceProviderCatalog title="Service Provider Catalog" description="Service Provider Catalog">
      <serviceProviders title="Service Provider" description="Service Provider">
        <services>
          <domainSpecification href="../model-domain-pddl/spec.xmi#//@domainSpecifications[name='SCOTT%20PDDL%202.1%20subset%20spec']"/>
          <basicCapabilities/>
        </services>
      </serviceProviders>
    </serviceProviderCatalog>
    <specification/>
    <requiredAdaptors xsi:type="oslc4j_ai:GenericRequiredAdaptor" serviceProviderCatalogURI="http://your.host.com/adaptor/services/catalog/singleton" name="GenericRequiredAdaptor"/>
  </adaptorInterfaces>
  <adaptorInterfaces name="LocationService" javaClassBaseNamespace="se.ericsson.cf.scott.sandbox.svc.location" javaFilesBasePath="../webapp-svc-location/src/main/java/" jspFilesBasePath="../webapp-svc-location/src/main/webapp/" javascriptFilesBasePath="../webapp-svc-location/src/main/webapp/">
    <serviceProviderCatalog title="Service Provider Catalog" description="Service Provider Catalog">
      <serviceProviders title="Service Provider" description="Service Provider">
        <services>
          <domainSpecification href="../model-domain-pddl/spec.xmi#//@domainSpecifications[name='Twins%20Domain']"/>
          <basicCapabilities/>
        </services>
      </serviceProviders>
    </serviceProviderCatalog>
    <specification/>
    <requiredAdaptors xsi:type="oslc4j_ai:GenericRequiredAdaptor" serviceProviderCatalogURI="http://your.host.com/adaptor/services/catalog/singleton" name="GenericRequiredAdaptor"/>
  </adaptorInterfaces>
  <specification>
    <domainSpecifications name="MissionOntology" namespaceURI="http://ontology.cf.ericsson.net/mission_ontology/" namespacePrefix="//@specification/@domainPrefixes[name='mission']">
      <resources name="Goal"/>
      <resources name="MoveGoal" extends="//@specification/@domainSpecifications[name='MissionOntology']/@resources[name='Goal']" resourceProperties="//@specification/@domainSpecifications[name='MissionOntology']/@resourceProperties[name='selector'] //@specification/@domainSpecifications[name='MissionOntology']/@resourceProperties[name='destination']"/>
      <resources name="Selector"/>
      <resources name="DirectSelector" extends="//@specification/@domainSpecifications[name='MissionOntology']/@resources[name='Selector']" resourceProperties="//@specification/@domainSpecifications[name='MissionOntology']/@resourceProperties[name='item']"/>
      <resources name="TypeSelector" extends="//@specification/@domainSpecifications[name='MissionOntology']/@resources[name='Selector']" resourceProperties="//@specification/@domainSpecifications[name='MissionOntology']/@resourceProperties[name='itemType'] //@specification/@domainSpecifications[name='MissionOntology']/@resourceProperties[name='count']"/>
      <resources name="WildcardSelector" extends="//@specification/@domainSpecifications[name='MissionOntology']/@resources[name='Selector']" resourceProperties="//@specification/@domainSpecifications[name='MissionOntology']/@resourceProperties[name='itemType']"/>
      <resources name="CompositeSelector" extends="//@specification/@domainSpecifications[name='MissionOntology']/@resources[name='Selector']" resourceProperties="//@specification/@domainSpecifications[name='MissionOntology']/@resourceProperties[name='selector']"/>
      <resources name="LocationSelector" extends="//@specification/@domainSpecifications[name='MissionOntology']/@resources[name='Selector']" resourceProperties="//@specification/@domainSpecifications[name='MissionOntology']/@resourceProperties[name='selector'] //@specification/@domainSpecifications[name='MissionOntology']/@resourceProperties[name='location']"/>
      <resources name="Location"/>
      <resources name="Mission" resourceProperties="//@specification/@domainSpecifications[name='MissionOntology']/@resourceProperties[name='goal'] //@specification/@domainSpecifications[name='MissionOntology']/@resourceProperties[name='responseTimeout'] //@specification/@domainSpecifications[name='MissionOntology']/@resourceProperties[name='missionDeadline']"/>
      <resources name="AgentRequest" resourceProperties="//@specification/@domainSpecifications[name='MissionOntology']/@resourceProperties[name='adaptor_id'] //@specification/@domainSpecifications[name='MissionOntology']/@resourceProperties[name='trs_topic'] //@specification/@domainSpecifications[name='MissionOntology']/@resourceProperties[name='trs_server']"/>
      <resources name="RegistrationRequest" extends="//@specification/@domainSpecifications[name='MissionOntology']/@resources[name='AgentRequest']"/>
      <resources name="DeregistrationRequest" extends="//@specification/@domainSpecifications[name='MissionOntology']/@resources[name='AgentRequest']"/>
      <resourceProperties title="" name="selector" valueType="LocalResource" representation="reference" range="//@specification/@domainSpecifications[name='MissionOntology']/@resources[name='Selector']"/>
      <resourceProperties name="destination" valueType="Resource" range="//@specification/@domainSpecifications[name='MissionOntology']/@resources[name='Location']"/>
      <resourceProperties name="item" valueType="Resource"/>
      <resourceProperties name="itemType" valueType="Resource"/>
      <resourceProperties name="count" valueType="Integer"/>
      <resourceProperties name="responseTimeout" valueType="Double"/>
      <resourceProperties name="missionDeadline" valueType="DateTime"/>
      <resourceProperties name="goal" valueType="LocalResource" range="//@specification/@domainSpecifications[name='MissionOntology']/@resources[name='Goal']"/>
      <resourceProperties name="location" valueType="Resource" range="//@specification/@domainSpecifications[name='MissionOntology']/@resources[name='Location']"/>
      <resourceProperties name="adaptor_id" valueType="String"/>
      <resourceProperties title="" name="trs_topic" valueType="URI" description="Should be a field on the TRS Server resource, but it's too much work to extend it now"/>
      <resourceProperties name="trs_server" valueType="URI"/>
      <generationSetting javaClassPackageName="eu.scott.warehouse.domains.mission" javaFilesPath="../domain-pddl/src/main/java"/>
    </domainSpecifications>
    <domainPrefixes name="mission"/>
    <generationSetting javaClassPackageName="my.package1" javaFilesPath="sandbox-domain-pddl/src/main/java"/>
  </specification>
  <vocabularies/>
</oslc4j_tc:Toolchain>
